<?xml version="1.0" encoding="UTF-8"?>
<con:soapui-project id="b047c85b-64c6-465e-a270-e75b4f84809e" activeEnvironment="Default" name="OuvrageService" resourceRoot="" soapui-version="5.4.0" xmlns:con="http://eviware.com/soapui/config"><con:settings/><con:interface xsi:type="con:WsdlInterface" id="e2a13e8f-e2f3-4100-abe3-cff66c37944e" wsaVersion="NONE" name="OuvrageServicePortBinding" type="wsdl" bindingName="{http://webService.wsBiblio.khady.fr/}OuvrageServicePortBinding" soapVersion="1_1" anonymous="optional" definition="http://lfr003015:8080/wsBiblio/OuvrageService?wsdl" xmlns:xsi="http://www.w3.org/2001/XMLSchema-instance"><con:settings/><con:definitionCache type="TEXT" rootPart="http://lfr003015:8080/wsBiblio/OuvrageService?wsdl"><con:part><con:url>http://lfr003015:8080/wsBiblio/OuvrageService?wsdl</con:url><con:content><![CDATA[<!--Published by JAX-WS RI (http://jax-ws.java.net). RI's version is Metro/2.4.0 (wsit240-7e98ff4; 2017-08-03T21:19:54+0200) JAXWS-RI/2.3.0 JAXWS-API/2.3.0 JAXB-RI/2.3.0 JAXB-API/2.3.0 svn-revision#unknown.-->
<!--Generated by JAX-WS RI (http://javaee.github.io/metro-jax-ws). RI's version is Metro/2.4.0 (wsit240-7e98ff4; 2017-08-03T21:19:54+0200) JAXWS-RI/2.3.0 JAXWS-API/2.3.0 JAXB-RI/2.3.0 JAXB-API/2.3.0 svn-revision#unknown.-->
<definitions targetNamespace="http://webService.wsBiblio.khady.fr/" name="OuvrageService" xmlns:wsu="http://docs.oasis-open.org/wss/2004/01/oasis-200401-wss-wssecurity-utility-1.0.xsd" xmlns:wsp="http://www.w3.org/ns/ws-policy" xmlns:wsp1_2="http://schemas.xmlsoap.org/ws/2004/09/policy" xmlns:wsam="http://www.w3.org/2007/05/addressing/metadata" xmlns:soap="http://schemas.xmlsoap.org/wsdl/soap/" xmlns:tns="http://webService.wsBiblio.khady.fr/" xmlns:xsd="http://www.w3.org/2001/XMLSchema" xmlns="http://schemas.xmlsoap.org/wsdl/">
  <types>
    <xsd:schema>
      <xsd:import namespace="http://webService.wsBiblio.khady.fr/" schemaLocation="http://lfr003015:8080/wsBiblio/OuvrageService?xsd=1"/>
    </xsd:schema>
  </types>
  <message name="trouverOuvrageParId">
    <part name="parameters" element="tns:trouverOuvrageParId"/>
  </message>
  <message name="trouverOuvrageParIdResponse">
    <part name="parameters" element="tns:trouverOuvrageParIdResponse"/>
  </message>
  <message name="BibliothequeException">
    <part name="fault" element="tns:BibliothequeException"/>
  </message>
  <message name="trouverOuvrageParIsbn">
    <part name="parameters" element="tns:trouverOuvrageParIsbn"/>
  </message>
  <message name="trouverOuvrageParIsbnResponse">
    <part name="parameters" element="tns:trouverOuvrageParIsbnResponse"/>
  </message>
  <message name="trouverOuvrageParAuteur">
    <part name="parameters" element="tns:trouverOuvrageParAuteur"/>
  </message>
  <message name="trouverOuvrageParAuteurResponse">
    <part name="parameters" element="tns:trouverOuvrageParAuteurResponse"/>
  </message>
  <message name="trouverOuvrageParTitre">
    <part name="parameters" element="tns:trouverOuvrageParTitre"/>
  </message>
  <message name="trouverOuvrageParTitreResponse">
    <part name="parameters" element="tns:trouverOuvrageParTitreResponse"/>
  </message>
  <message name="trouverOuvrageParCategorie">
    <part name="parameters" element="tns:trouverOuvrageParCategorie"/>
  </message>
  <message name="trouverOuvrageParCategorieResponse">
    <part name="parameters" element="tns:trouverOuvrageParCategorieResponse"/>
  </message>
  <message name="trouverOuvrageParIsbnTitreAuteur">
    <part name="parameters" element="tns:trouverOuvrageParIsbnTitreAuteur"/>
  </message>
  <message name="trouverOuvrageParIsbnTitreAuteurResponse">
    <part name="parameters" element="tns:trouverOuvrageParIsbnTitreAuteurResponse"/>
  </message>
  <message name="trouverOuvrageParDisponiblite">
    <part name="parameters" element="tns:trouverOuvrageParDisponiblite"/>
  </message>
  <message name="trouverOuvrageParDisponibliteResponse">
    <part name="parameters" element="tns:trouverOuvrageParDisponibliteResponse"/>
  </message>
  <message name="listerOuvrage">
    <part name="parameters" element="tns:listerOuvrage"/>
  </message>
  <message name="listerOuvrageResponse">
    <part name="parameters" element="tns:listerOuvrageResponse"/>
  </message>
  <message name="creerOuvrage">
    <part name="parameters" element="tns:creerOuvrage"/>
  </message>
  <message name="creerOuvrageResponse">
    <part name="parameters" element="tns:creerOuvrageResponse"/>
  </message>
  <portType name="OuvrageService">
    <operation name="trouverOuvrageParId">
      <input wsam:Action="http://webService.wsBiblio.khady.fr/OuvrageService/trouverOuvrageParIdRequest" message="tns:trouverOuvrageParId"/>
      <output wsam:Action="http://webService.wsBiblio.khady.fr/OuvrageService/trouverOuvrageParIdResponse" message="tns:trouverOuvrageParIdResponse"/>
      <fault message="tns:BibliothequeException" name="BibliothequeException" wsam:Action="http://webService.wsBiblio.khady.fr/OuvrageService/trouverOuvrageParId/Fault/BibliothequeException"/>
    </operation>
    <operation name="trouverOuvrageParIsbn">
      <input wsam:Action="http://webService.wsBiblio.khady.fr/OuvrageService/trouverOuvrageParIsbnRequest" message="tns:trouverOuvrageParIsbn"/>
      <output wsam:Action="http://webService.wsBiblio.khady.fr/OuvrageService/trouverOuvrageParIsbnResponse" message="tns:trouverOuvrageParIsbnResponse"/>
      <fault message="tns:BibliothequeException" name="BibliothequeException" wsam:Action="http://webService.wsBiblio.khady.fr/OuvrageService/trouverOuvrageParIsbn/Fault/BibliothequeException"/>
    </operation>
    <operation name="trouverOuvrageParAuteur">
      <input wsam:Action="http://webService.wsBiblio.khady.fr/OuvrageService/trouverOuvrageParAuteurRequest" message="tns:trouverOuvrageParAuteur"/>
      <output wsam:Action="http://webService.wsBiblio.khady.fr/OuvrageService/trouverOuvrageParAuteurResponse" message="tns:trouverOuvrageParAuteurResponse"/>
      <fault message="tns:BibliothequeException" name="BibliothequeException" wsam:Action="http://webService.wsBiblio.khady.fr/OuvrageService/trouverOuvrageParAuteur/Fault/BibliothequeException"/>
    </operation>
    <operation name="trouverOuvrageParTitre">
      <input wsam:Action="http://webService.wsBiblio.khady.fr/OuvrageService/trouverOuvrageParTitreRequest" message="tns:trouverOuvrageParTitre"/>
      <output wsam:Action="http://webService.wsBiblio.khady.fr/OuvrageService/trouverOuvrageParTitreResponse" message="tns:trouverOuvrageParTitreResponse"/>
      <fault message="tns:BibliothequeException" name="BibliothequeException" wsam:Action="http://webService.wsBiblio.khady.fr/OuvrageService/trouverOuvrageParTitre/Fault/BibliothequeException"/>
    </operation>
    <operation name="trouverOuvrageParCategorie">
      <input wsam:Action="http://webService.wsBiblio.khady.fr/OuvrageService/trouverOuvrageParCategorieRequest" message="tns:trouverOuvrageParCategorie"/>
      <output wsam:Action="http://webService.wsBiblio.khady.fr/OuvrageService/trouverOuvrageParCategorieResponse" message="tns:trouverOuvrageParCategorieResponse"/>
      <fault message="tns:BibliothequeException" name="BibliothequeException" wsam:Action="http://webService.wsBiblio.khady.fr/OuvrageService/trouverOuvrageParCategorie/Fault/BibliothequeException"/>
    </operation>
    <operation name="trouverOuvrageParIsbnTitreAuteur">
      <input wsam:Action="http://webService.wsBiblio.khady.fr/OuvrageService/trouverOuvrageParIsbnTitreAuteurRequest" message="tns:trouverOuvrageParIsbnTitreAuteur"/>
      <output wsam:Action="http://webService.wsBiblio.khady.fr/OuvrageService/trouverOuvrageParIsbnTitreAuteurResponse" message="tns:trouverOuvrageParIsbnTitreAuteurResponse"/>
      <fault message="tns:BibliothequeException" name="BibliothequeException" wsam:Action="http://webService.wsBiblio.khady.fr/OuvrageService/trouverOuvrageParIsbnTitreAuteur/Fault/BibliothequeException"/>
    </operation>
    <operation name="trouverOuvrageParDisponiblite">
      <input wsam:Action="http://webService.wsBiblio.khady.fr/OuvrageService/trouverOuvrageParDisponibliteRequest" message="tns:trouverOuvrageParDisponiblite"/>
      <output wsam:Action="http://webService.wsBiblio.khady.fr/OuvrageService/trouverOuvrageParDisponibliteResponse" message="tns:trouverOuvrageParDisponibliteResponse"/>
      <fault message="tns:BibliothequeException" name="BibliothequeException" wsam:Action="http://webService.wsBiblio.khady.fr/OuvrageService/trouverOuvrageParDisponiblite/Fault/BibliothequeException"/>
    </operation>
    <operation name="listerOuvrage">
      <input wsam:Action="http://webService.wsBiblio.khady.fr/OuvrageService/listerOuvrageRequest" message="tns:listerOuvrage"/>
      <output wsam:Action="http://webService.wsBiblio.khady.fr/OuvrageService/listerOuvrageResponse" message="tns:listerOuvrageResponse"/>
    </operation>
    <operation name="creerOuvrage">
      <input wsam:Action="http://webService.wsBiblio.khady.fr/OuvrageService/creerOuvrageRequest" message="tns:creerOuvrage"/>
      <output wsam:Action="http://webService.wsBiblio.khady.fr/OuvrageService/creerOuvrageResponse" message="tns:creerOuvrageResponse"/>
    </operation>
  </portType>
  <binding name="OuvrageServicePortBinding" type="tns:OuvrageService">
    <soap:binding transport="http://schemas.xmlsoap.org/soap/http" style="document"/>
    <operation name="trouverOuvrageParId">
      <soap:operation soapAction=""/>
      <input>
        <soap:body use="literal"/>
      </input>
      <output>
        <soap:body use="literal"/>
      </output>
      <fault name="BibliothequeException">
        <soap:fault name="BibliothequeException" use="literal"/>
      </fault>
    </operation>
    <operation name="trouverOuvrageParIsbn">
      <soap:operation soapAction=""/>
      <input>
        <soap:body use="literal"/>
      </input>
      <output>
        <soap:body use="literal"/>
      </output>
      <fault name="BibliothequeException">
        <soap:fault name="BibliothequeException" use="literal"/>
      </fault>
    </operation>
    <operation name="trouverOuvrageParAuteur">
      <soap:operation soapAction=""/>
      <input>
        <soap:body use="literal"/>
      </input>
      <output>
        <soap:body use="literal"/>
      </output>
      <fault name="BibliothequeException">
        <soap:fault name="BibliothequeException" use="literal"/>
      </fault>
    </operation>
    <operation name="trouverOuvrageParTitre">
      <soap:operation soapAction=""/>
      <input>
        <soap:body use="literal"/>
      </input>
      <output>
        <soap:body use="literal"/>
      </output>
      <fault name="BibliothequeException">
        <soap:fault name="BibliothequeException" use="literal"/>
      </fault>
    </operation>
    <operation name="trouverOuvrageParCategorie">
      <soap:operation soapAction=""/>
      <input>
        <soap:body use="literal"/>
      </input>
      <output>
        <soap:body use="literal"/>
      </output>
      <fault name="BibliothequeException">
        <soap:fault name="BibliothequeException" use="literal"/>
      </fault>
    </operation>
    <operation name="trouverOuvrageParIsbnTitreAuteur">
      <soap:operation soapAction=""/>
      <input>
        <soap:body use="literal"/>
      </input>
      <output>
        <soap:body use="literal"/>
      </output>
      <fault name="BibliothequeException">
        <soap:fault name="BibliothequeException" use="literal"/>
      </fault>
    </operation>
    <operation name="trouverOuvrageParDisponiblite">
      <soap:operation soapAction=""/>
      <input>
        <soap:body use="literal"/>
      </input>
      <output>
        <soap:body use="literal"/>
      </output>
      <fault name="BibliothequeException">
        <soap:fault name="BibliothequeException" use="literal"/>
      </fault>
    </operation>
    <operation name="listerOuvrage">
      <soap:operation soapAction=""/>
      <input>
        <soap:body use="literal"/>
      </input>
      <output>
        <soap:body use="literal"/>
      </output>
    </operation>
    <operation name="creerOuvrage">
      <soap:operation soapAction=""/>
      <input>
        <soap:body use="literal"/>
      </input>
      <output>
        <soap:body use="literal"/>
      </output>
    </operation>
  </binding>
  <service name="OuvrageService">
    <port name="OuvrageServicePort" binding="tns:OuvrageServicePortBinding">
      <soap:address location="http://lfr003015:8080/wsBiblio/OuvrageService"/>
    </port>
  </service>
</definitions>]]></con:content><con:type>http://schemas.xmlsoap.org/wsdl/</con:type></con:part><con:part><con:url>http://lfr003015:8080/wsBiblio/OuvrageService?xsd=1</con:url><con:content><![CDATA[<!--Published by JAX-WS RI (http://jax-ws.java.net). RI's version is Metro/2.4.0 (wsit240-7e98ff4; 2017-08-03T21:19:54+0200) JAXWS-RI/2.3.0 JAXWS-API/2.3.0 JAXB-RI/2.3.0 JAXB-API/2.3.0 svn-revision#unknown.-->
<xs:schema version="1.0" targetNamespace="http://webService.wsBiblio.khady.fr/" xmlns:tns="http://webService.wsBiblio.khady.fr/" xmlns:xs="http://www.w3.org/2001/XMLSchema">
  <xs:element name="BibliothequeException" nillable="true" type="tns:bibliothequeFault"/>
  <xs:element name="creerOuvrage" type="tns:creerOuvrage"/>
  <xs:element name="creerOuvrageResponse" type="tns:creerOuvrageResponse"/>
  <xs:element name="listerOuvrage" type="tns:listerOuvrage"/>
  <xs:element name="listerOuvrageResponse" type="tns:listerOuvrageResponse"/>
  <xs:element name="trouverOuvrageParAuteur" type="tns:trouverOuvrageParAuteur"/>
  <xs:element name="trouverOuvrageParAuteurResponse" type="tns:trouverOuvrageParAuteurResponse"/>
  <xs:element name="trouverOuvrageParCategorie" type="tns:trouverOuvrageParCategorie"/>
  <xs:element name="trouverOuvrageParCategorieResponse" type="tns:trouverOuvrageParCategorieResponse"/>
  <xs:element name="trouverOuvrageParDisponiblite" type="tns:trouverOuvrageParDisponiblite"/>
  <xs:element name="trouverOuvrageParDisponibliteResponse" type="tns:trouverOuvrageParDisponibliteResponse"/>
  <xs:element name="trouverOuvrageParId" type="tns:trouverOuvrageParId"/>
  <xs:element name="trouverOuvrageParIdResponse" type="tns:trouverOuvrageParIdResponse"/>
  <xs:element name="trouverOuvrageParIsbn" type="tns:trouverOuvrageParIsbn"/>
  <xs:element name="trouverOuvrageParIsbnResponse" type="tns:trouverOuvrageParIsbnResponse"/>
  <xs:element name="trouverOuvrageParIsbnTitreAuteur" type="tns:trouverOuvrageParIsbnTitreAuteur"/>
  <xs:element name="trouverOuvrageParIsbnTitreAuteurResponse" type="tns:trouverOuvrageParIsbnTitreAuteurResponse"/>
  <xs:element name="trouverOuvrageParTitre" type="tns:trouverOuvrageParTitre"/>
  <xs:element name="trouverOuvrageParTitreResponse" type="tns:trouverOuvrageParTitreResponse"/>
  <xs:complexType name="trouverOuvrageParIsbnTitreAuteur">
    <xs:sequence>
      <xs:element name="isbn" type="xs:string" minOccurs="0"/>
      <xs:element name="titre" type="xs:string" minOccurs="0"/>
      <xs:element name="auteur" type="xs:string" minOccurs="0"/>
      <xs:element name="disponibilité" type="xs:boolean" minOccurs="0"/>
    </xs:sequence>
  </xs:complexType>
  <xs:complexType name="trouverOuvrageParIsbnTitreAuteurResponse">
    <xs:sequence>
      <xs:element name="return" type="tns:ouvrage" minOccurs="0" maxOccurs="unbounded"/>
    </xs:sequence>
  </xs:complexType>
  <xs:complexType name="ouvrage">
    <xs:sequence>
      <xs:element name="auteur" type="tns:auteur" minOccurs="0"/>
      <xs:element name="categorie" type="tns:categorie" minOccurs="0"/>
      <xs:element name="dateParution" type="xs:dateTime" minOccurs="0"/>
      <xs:element name="disponibilite" type="xs:boolean" minOccurs="0"/>
      <xs:element name="idOuvrage" type="xs:long"/>
      <xs:element name="isbn" type="xs:string" minOccurs="0"/>
      <xs:element name="nbrpage" type="xs:int"/>
      <xs:element name="photoCouverture" type="xs:string" minOccurs="0"/>
      <xs:element name="resume" type="xs:string" minOccurs="0"/>
      <xs:element name="titre" type="xs:string" minOccurs="0"/>
    </xs:sequence>
  </xs:complexType>
  <xs:complexType name="auteur">
    <xs:sequence>
      <xs:element name="dateNaiss" type="xs:dateTime" minOccurs="0"/>
      <xs:element name="idAuteur" type="xs:long"/>
      <xs:element name="nom" type="xs:string" minOccurs="0"/>
      <xs:element name="prenom" type="xs:string" minOccurs="0"/>
    </xs:sequence>
  </xs:complexType>
  <xs:complexType name="categorie">
    <xs:sequence>
      <xs:element name="idCat" type="xs:long"/>
      <xs:element name="libelle" type="xs:string" minOccurs="0"/>
    </xs:sequence>
  </xs:complexType>
  <xs:complexType name="bibliothequeFault">
    <xs:sequence>
      <xs:element name="faultCode" type="xs:string" minOccurs="0"/>
      <xs:element name="faultString" type="xs:string" minOccurs="0"/>
    </xs:sequence>
  </xs:complexType>
  <xs:complexType name="trouverOuvrageParAuteur">
    <xs:sequence>
      <xs:element name="arg0" type="xs:long"/>
    </xs:sequence>
  </xs:complexType>
  <xs:complexType name="trouverOuvrageParAuteurResponse">
    <xs:sequence>
      <xs:element name="return" type="tns:ouvrage" minOccurs="0" maxOccurs="unbounded"/>
    </xs:sequence>
  </xs:complexType>
  <xs:complexType name="trouverOuvrageParDisponiblite">
    <xs:sequence>
      <xs:element name="arg0" type="xs:boolean" minOccurs="0"/>
    </xs:sequence>
  </xs:complexType>
  <xs:complexType name="trouverOuvrageParDisponibliteResponse">
    <xs:sequence>
      <xs:element name="return" type="tns:ouvrage" minOccurs="0" maxOccurs="unbounded"/>
    </xs:sequence>
  </xs:complexType>
  <xs:complexType name="listerOuvrage">
    <xs:sequence/>
  </xs:complexType>
  <xs:complexType name="listerOuvrageResponse">
    <xs:sequence>
      <xs:element name="return" type="tns:ouvrage" minOccurs="0" maxOccurs="unbounded"/>
    </xs:sequence>
  </xs:complexType>
  <xs:complexType name="trouverOuvrageParIsbn">
    <xs:sequence>
      <xs:element name="arg0" type="xs:string" minOccurs="0"/>
    </xs:sequence>
  </xs:complexType>
  <xs:complexType name="trouverOuvrageParIsbnResponse">
    <xs:sequence>
      <xs:element name="return" type="tns:ouvrage" minOccurs="0" maxOccurs="unbounded"/>
    </xs:sequence>
  </xs:complexType>
  <xs:complexType name="creerOuvrage">
    <xs:sequence>
      <xs:element name="isbn" type="xs:string" minOccurs="0"/>
      <xs:element name="titre" type="xs:string" minOccurs="0"/>
      <xs:element name="resume" type="xs:string" minOccurs="0"/>
      <xs:element name="nbrpage" type="xs:int"/>
      <xs:element name="dateParution" type="xs:dateTime" minOccurs="0"/>
      <xs:element name="disponibilite" type="xs:boolean" minOccurs="0"/>
      <xs:element name="photoCouverture" type="xs:string" minOccurs="0"/>
      <xs:element name="categorie" type="xs:long"/>
      <xs:element name="auteur" type="xs:long"/>
    </xs:sequence>
  </xs:complexType>
  <xs:complexType name="creerOuvrageResponse">
    <xs:sequence/>
  </xs:complexType>
  <xs:complexType name="trouverOuvrageParId">
    <xs:sequence>
      <xs:element name="idOuvrage" type="xs:long"/>
    </xs:sequence>
  </xs:complexType>
  <xs:complexType name="trouverOuvrageParIdResponse">
    <xs:sequence>
      <xs:element name="return" type="tns:ouvrage" minOccurs="0"/>
    </xs:sequence>
  </xs:complexType>
  <xs:complexType name="trouverOuvrageParCategorie">
    <xs:sequence>
      <xs:element name="arg0" type="xs:long"/>
    </xs:sequence>
  </xs:complexType>
  <xs:complexType name="trouverOuvrageParCategorieResponse">
    <xs:sequence>
      <xs:element name="return" type="tns:ouvrage" minOccurs="0"/>
    </xs:sequence>
  </xs:complexType>
  <xs:complexType name="trouverOuvrageParTitre">
    <xs:sequence>
      <xs:element name="arg0" type="xs:string" minOccurs="0"/>
    </xs:sequence>
  </xs:complexType>
  <xs:complexType name="trouverOuvrageParTitreResponse">
    <xs:sequence>
      <xs:element name="return" type="tns:ouvrage" minOccurs="0" maxOccurs="unbounded"/>
    </xs:sequence>
  </xs:complexType>
</xs:schema>]]></con:content><con:type>http://www.w3.org/2001/XMLSchema</con:type></con:part></con:definitionCache><con:endpoints><con:endpoint>http://lfr003015:8080/wsBiblio/OuvrageService</con:endpoint></con:endpoints><con:operation id="dff7b761-0454-4338-b5fb-5919dc45f501" isOneWay="false" action="" name="creerOuvrage" bindingOperationName="creerOuvrage" type="Request-Response" inputName="" receivesAttachments="false" sendsAttachments="false" anonymous="optional"><con:settings/><con:call id="1506dc96-f6d8-4f6b-abfe-60c2b0704912" name="Request 1"><con:settings/><con:encoding>UTF-8</con:encoding><con:endpoint>http://lfr003015:8080/wsBiblio/OuvrageService</con:endpoint><con:request><![CDATA[<soapenv:Envelope xmlns:soapenv="http://schemas.xmlsoap.org/soap/envelope/" xmlns:web="http://webService.wsBiblio.khady.fr/">\r
   <soapenv:Header/>\r
   <soapenv:Body>\r
      <web:creerOuvrage>\r
         <!--Optional:-->\r
         <isbn>?</isbn>\r
         <!--Optional:-->\r
         <titre>?</titre>\r
         <!--Optional:-->\r
         <resume>?</resume>\r
         <nbrpage>?</nbrpage>\r
         <!--Optional:-->\r
         <dateParution>?</dateParution>\r
         <!--Optional:-->\r
         <disponibilite>?</disponibilite>\r
         <!--Optional:-->\r
         <photoCouverture>?</photoCouverture>\r
         <categorie>?</categorie>\r
         <auteur>?</auteur>\r
      </web:creerOuvrage>\r
   </soapenv:Body>\r
</soapenv:Envelope>]]></con:request><con:credentials><con:authType>No Authorization</con:authType></con:credentials><con:jmsConfig JMSDeliveryMode="PERSISTENT"/><con:jmsPropertyConfig/><con:wsaConfig mustUnderstand="NONE" version="200508" action="http://webService.wsBiblio.khady.fr/OuvrageService/creerOuvrageRequest"/><con:wsrmConfig version="1.2"/></con:call></con:operation><con:operation id="4c8caaf8-919f-4ce0-b027-3b0c7d2bf3f9" isOneWay="false" action="" name="listerOuvrage" bindingOperationName="listerOuvrage" type="Request-Response" inputName="" receivesAttachments="false" sendsAttachments="false" anonymous="optional"><con:settings/><con:call id="ad544068-fbd3-4bd4-8253-9826e5452d0f" name="Request 1"><con:settings/><con:encoding>UTF-8</con:encoding><con:endpoint>http://lfr003015:8080/wsBiblio/OuvrageService</con:endpoint><con:request><![CDATA[<soapenv:Envelope xmlns:soapenv="http://schemas.xmlsoap.org/soap/envelope/" xmlns:web="http://webService.wsBiblio.khady.fr/">\r
   <soapenv:Header/>\r
   <soapenv:Body>\r
      <web:listerOuvrage/>\r
   </soapenv:Body>\r
</soapenv:Envelope>]]></con:request><con:wsaConfig mustUnderstand="NONE" version="200508" action="http://webService.wsBiblio.khady.fr/OuvrageService/listerOuvrageRequest"/></con:call></con:operation><con:operation id="6ca8554a-3acd-4b1f-90de-45c0ad16b563" isOneWay="false" action="" name="trouverOuvrageParAuteur" bindingOperationName="trouverOuvrageParAuteur" type="Request-Response" inputName="" receivesAttachments="false" sendsAttachments="false" anonymous="optional"><con:settings/><con:call id="c19c277d-9e39-40f7-bd4f-2e82790d4fc6" name="Request 1"><con:settings/><con:encoding>UTF-8</con:encoding><con:endpoint>http://lfr003015:8080/wsBiblio/OuvrageService</con:endpoint><con:request><![CDATA[<soapenv:Envelope xmlns:soapenv="http://schemas.xmlsoap.org/soap/envelope/" xmlns:web="http://webService.wsBiblio.khady.fr/">\r
   <soapenv:Header/>\r
   <soapenv:Body>\r
      <web:trouverOuvrageParAuteur>\r
         <arg0>?</arg0>\r
      </web:trouverOuvrageParAuteur>\r
   </soapenv:Body>\r
</soapenv:Envelope>]]></con:request><con:wsaConfig mustUnderstand="NONE" version="200508" action="http://webService.wsBiblio.khady.fr/OuvrageService/trouverOuvrageParAuteurRequest"/></con:call></con:operation><con:operation id="3ce86e5f-72e8-442d-9e97-1f9f8ea2884a" isOneWay="false" action="" name="trouverOuvrageParCategorie" bindingOperationName="trouverOuvrageParCategorie" type="Request-Response" inputName="" receivesAttachments="false" sendsAttachments="false" anonymous="optional"><con:settings/><con:call id="80e75351-a639-4f8a-b700-e51b2f3b5980" name="Request 1"><con:settings/><con:encoding>UTF-8</con:encoding><con:endpoint>http://lfr003015:8080/wsBiblio/OuvrageService</con:endpoint><con:request><![CDATA[<soapenv:Envelope xmlns:soapenv="http://schemas.xmlsoap.org/soap/envelope/" xmlns:web="http://webService.wsBiblio.khady.fr/">\r
   <soapenv:Header/>\r
   <soapenv:Body>\r
      <web:trouverOuvrageParCategorie>\r
         <arg0>?</arg0>\r
      </web:trouverOuvrageParCategorie>\r
   </soapenv:Body>\r
</soapenv:Envelope>]]></con:request><con:wsaConfig mustUnderstand="NONE" version="200508" action="http://webService.wsBiblio.khady.fr/OuvrageService/trouverOuvrageParCategorieRequest"/></con:call></con:operation><con:operation id="8b0cd8d8-e47f-4d00-8ae2-b6e38502fcb5" isOneWay="false" action="" name="trouverOuvrageParDisponiblite" bindingOperationName="trouverOuvrageParDisponiblite" type="Request-Response" inputName="" receivesAttachments="false" sendsAttachments="false" anonymous="optional"><con:settings/><con:call id="03ab7a73-a2c9-4bc1-ad8d-fbdd9dbd00bb" name="Request 1"><con:settings/><con:encoding>UTF-8</con:encoding><con:endpoint>http://lfr003015:8080/wsBiblio/OuvrageService</con:endpoint><con:request><![CDATA[<soapenv:Envelope xmlns:soapenv="http://schemas.xmlsoap.org/soap/envelope/" xmlns:web="http://webService.wsBiblio.khady.fr/">\r
   <soapenv:Header/>\r
   <soapenv:Body>\r
      <web:trouverOuvrageParDisponiblite>\r
         <!--Optional:-->\r
         <arg0>?</arg0>\r
      </web:trouverOuvrageParDisponiblite>\r
   </soapenv:Body>\r
</soapenv:Envelope>]]></con:request><con:wsaConfig mustUnderstand="NONE" version="200508" action="http://webService.wsBiblio.khady.fr/OuvrageService/trouverOuvrageParDisponibliteRequest"/></con:call></con:operation><con:operation id="cf9ee5e6-0ee3-4a48-8174-7d8fc66c1507" isOneWay="false" action="" name="trouverOuvrageParId" bindingOperationName="trouverOuvrageParId" type="Request-Response" inputName="" receivesAttachments="false" sendsAttachments="false" anonymous="optional"><con:settings/><con:call id="5d2533d2-c76e-41a6-ac14-b5f690e8517c" name="Request 1"><con:settings/><con:encoding>UTF-8</con:encoding><con:endpoint>http://lfr003015:8080/wsBiblio/OuvrageService</con:endpoint><con:request><![CDATA[<soapenv:Envelope xmlns:soapenv="http://schemas.xmlsoap.org/soap/envelope/" xmlns:web="http://webService.wsBiblio.khady.fr/">\r
   <soapenv:Header/>\r
   <soapenv:Body>\r
      <web:trouverOuvrageParId>\r
         <idOuvrage>?</idOuvrage>\r
      </web:trouverOuvrageParId>\r
   </soapenv:Body>\r
</soapenv:Envelope>]]></con:request><con:wsaConfig mustUnderstand="NONE" version="200508" action="http://webService.wsBiblio.khady.fr/OuvrageService/trouverOuvrageParIdRequest"/></con:call></con:operation><con:operation id="6e4ce363-65ed-4ca6-82fe-06489fecbd58" isOneWay="false" action="" name="trouverOuvrageParIsbn" bindingOperationName="trouverOuvrageParIsbn" type="Request-Response" inputName="" receivesAttachments="false" sendsAttachments="false" anonymous="optional"><con:settings/><con:call id="08f166ed-2f6a-4312-b8c8-41afee5ac511" name="Request 1"><con:settings/><con:encoding>UTF-8</con:encoding><con:endpoint>http://lfr003015:8080/wsBiblio/OuvrageService</con:endpoint><con:request><![CDATA[<soapenv:Envelope xmlns:soapenv="http://schemas.xmlsoap.org/soap/envelope/" xmlns:web="http://webService.wsBiblio.khady.fr/">\r
   <soapenv:Header/>\r
   <soapenv:Body>\r
      <web:trouverOuvrageParIsbn>\r
         <!--Optional:-->\r
         <arg0>?</arg0>\r
      </web:trouverOuvrageParIsbn>\r
   </soapenv:Body>\r
</soapenv:Envelope>]]></con:request><con:credentials><con:authType>No Authorization</con:authType></con:credentials><con:jmsConfig JMSDeliveryMode="PERSISTENT"/><con:jmsPropertyConfig/><con:wsaConfig mustUnderstand="NONE" version="200508" action="http://webService.wsBiblio.khady.fr/OuvrageService/trouverOuvrageParIsbnRequest"/><con:wsrmConfig version="1.2"/></con:call></con:operation><con:operation id="865cdb51-8298-416d-9004-670c97ecfdf3" isOneWay="false" action="" name="trouverOuvrageParIsbnTitreAuteur" bindingOperationName="trouverOuvrageParIsbnTitreAuteur" type="Request-Response" inputName="" receivesAttachments="false" sendsAttachments="false" anonymous="optional"><con:settings/><con:call id="eb01373f-b046-40b9-b9ed-28e0b80da66c" name="Request 1"><con:settings/><con:encoding>UTF-8</con:encoding><con:endpoint>http://lfr003015:8080/wsBiblio/OuvrageService</con:endpoint><con:request><![CDATA[<soapenv:Envelope xmlns:soapenv="http://schemas.xmlsoap.org/soap/envelope/" xmlns:web="http://webService.wsBiblio.khady.fr/">\r
   <soapenv:Header/>\r
   <soapenv:Body>\r
      <web:trouverOuvrageParIsbnTitreAuteur>\r
         <!--Optional:-->\r
         <isbn>?</isbn>\r
         <!--Optional:-->\r
         <titre>?</titre>\r
         <!--Optional:-->\r
         <auteur>?</auteur>\r
         <!--Optional:-->\r
         <disponibilité>?</disponibilité>\r
      </web:trouverOuvrageParIsbnTitreAuteur>\r
   </soapenv:Body>\r
</soapenv:Envelope>]]></con:request><con:wsaConfig mustUnderstand="NONE" version="200508" action="http://webService.wsBiblio.khady.fr/OuvrageService/trouverOuvrageParIsbnTitreAuteurRequest"/></con:call></con:operation><con:operation id="d1372512-0ff4-4f10-a50c-0c27ff5592f3" isOneWay="false" action="" name="trouverOuvrageParTitre" bindingOperationName="trouverOuvrageParTitre" type="Request-Response" inputName="" receivesAttachments="false" sendsAttachments="false" anonymous="optional"><con:settings/><con:call id="6cae8bc3-15fd-4c27-aad6-4f48f58f0705" name="Request 1"><con:settings/><con:encoding>UTF-8</con:encoding><con:endpoint>http://lfr003015:8080/wsBiblio/OuvrageService</con:endpoint><con:request><![CDATA[<soapenv:Envelope xmlns:soapenv="http://schemas.xmlsoap.org/soap/envelope/" xmlns:web="http://webService.wsBiblio.khady.fr/">\r
   <soapenv:Header/>\r
   <soapenv:Body>\r
      <web:trouverOuvrageParTitre>\r
         <!--Optional:-->\r
         <arg0>?</arg0>\r
      </web:trouverOuvrageParTitre>\r
   </soapenv:Body>\r
</soapenv:Envelope>]]></con:request><con:wsaConfig mustUnderstand="NONE" version="200508" action="http://webService.wsBiblio.khady.fr/OuvrageService/trouverOuvrageParTitreRequest"/></con:call></con:operation></con:interface><con:testSuite id="7b2af560-d7e2-4196-9c5c-8f85b958cb0c" name="TestSuite_Ouvrage"><con:settings/><con:runType>SEQUENTIAL</con:runType><con:testCase id="35890bc5-0c9a-4cb7-8036-298510ab0a0d" failOnError="true" failTestCaseOnErrors="true" keepSession="false" maxResults="0" name="TestCase_Ouvrage" searchProperties="true"><con:settings/><con:testStep type="request" id="621cd203-d576-4e21-a45c-9531355e43ac" name="creerOuvrage - Request 1"><con:settings/><con:config xsi:type="con:RequestStep" xmlns:xsi="http://www.w3.org/2001/XMLSchema-instance"><con:interface>OuvrageServicePortBinding</con:interface><con:operation>creerOuvrage</con:operation><con:request name="creerOuvrage - Request 1" outgoingWss="" incomingWss="" timeout="" sslKeystore="" useWsAddressing="false" useWsReliableMessaging="false" wssPasswordType="" id="ef3d087c-74b6-4708-b539-3dc185da2ca1"><con:settings><con:setting id="com.eviware.soapui.impl.wsdl.WsdlRequest@request-headers">&lt;xml-fragment/></con:setting></con:settings><con:encoding>UTF-8</con:encoding><con:endpoint>http://lfr003015:8080/wsBiblio/OuvrageService</con:endpoint><con:request><![CDATA[<soapenv:Envelope xmlns:soapenv="http://schemas.xmlsoap.org/soap/envelope/" xmlns:web="http://webService.wsBiblio.khady.fr/">\r
   <soapenv:Header/>\r
   <soapenv:Body>\r
      <web:creerOuvrage>\r
         <!--Optional:-->\r
         <isbn>${#TestCase#isbn}</isbn>\r
         <!--Optional:-->\r
         <titre>${#TestCase#titre}</titre>\r
         <!--Optional:-->\r
         <resume>${#TestCase#resume}</resume>\r
         <nbrpage>${#TestCase#nbrpage}</nbrpage>\r
         <!--Optional:-->\r
         <dateParution>${#TestCase#dateParution}</dateParution>\r
         <!--Optional:-->\r
         <disponibilite>${#TestCase#dispo}</disponibilite>\r
         <!--Optional:-->\r
         <photoCouverture>${#TestCase#photo}</photoCouverture>\r
         <categorie>${#TestCase#categorie}</categorie>\r
         <auteur>${#TestCase#auteur}</auteur>\r
      </web:creerOuvrage>\r
   </soapenv:Body>\r
</soapenv:Envelope>]]></con:request><con:assertion type="SOAP Response" id="432531ec-d247-462d-84d6-ed051ad89089" name="SOAP Response"/><con:credentials><con:authType>No Authorization</con:authType></con:credentials><con:jmsConfig JMSDeliveryMode="PERSISTENT"/><con:jmsPropertyConfig/><con:wsaConfig mustUnderstand="NONE" version="200508" action="http://webService.wsBiblio.khady.fr/OuvrageService/creerOuvrageRequest"/><con:wsrmConfig version="1.2"/></con:request></con:config></con:testStep><con:testStep type="request" id="7b9b9b74-9c5c-4388-acea-04757e84334b" name="listerOuvrage - Request 1"><con:settings/><con:config xsi:type="con:RequestStep" xmlns:xsi="http://www.w3.org/2001/XMLSchema-instance"><con:interface>OuvrageServicePortBinding</con:interface><con:operation>listerOuvrage</con:operation><con:request name="listerOuvrage - Request 1" outgoingWss="" incomingWss="" timeout="" sslKeystore="" useWsAddressing="false" useWsReliableMessaging="false" wssPasswordType="" id="00a7020c-d9da-4904-9f85-1c8c47e93049"><con:settings/><con:encoding>UTF-8</con:encoding><con:endpoint>http://lfr003015:8080/wsBiblio/OuvrageService</con:endpoint><con:request><![CDATA[<soapenv:Envelope xmlns:soapenv="http://schemas.xmlsoap.org/soap/envelope/" xmlns:web="http://webService.wsBiblio.khady.fr/">\r
   <soapenv:Header/>\r
   <soapenv:Body>\r
      <web:listerOuvrage/>\r
   </soapenv:Body>\r
</soapenv:Envelope>]]></con:request><con:assertion type="SOAP Response" id="c3f500d2-b82c-4367-8175-a70b38d2e3f7" name="SOAP Response"/><con:credentials><con:authType>No Authorization</con:authType></con:credentials><con:jmsConfig JMSDeliveryMode="PERSISTENT"/><con:jmsPropertyConfig/><con:wsaConfig mustUnderstand="NONE" version="200508" action="http://webService.wsBiblio.khady.fr/OuvrageService/listerOuvrageRequest"/><con:wsrmConfig version="1.2"/></con:request></con:config></con:testStep><con:testStep type="request" id="cfdf5542-faa4-43fe-b7f2-e41ab2279f36" name="trouverOuvrageParIsbnTitreAuteur - Request 1"><con:settings/><con:config xsi:type="con:RequestStep" xmlns:xsi="http://www.w3.org/2001/XMLSchema-instance"><con:interface>OuvrageServicePortBinding</con:interface><con:operation>trouverOuvrageParIsbnTitreAuteur</con:operation><con:request name="trouverOuvrageParIsbnTitreAuteur - Request 1" outgoingWss="" incomingWss="" timeout="" sslKeystore="" useWsAddressing="false" useWsReliableMessaging="false" wssPasswordType="" id="8762805d-7eae-4b48-9444-ee1275cc3276"><con:settings/><con:encoding>UTF-8</con:encoding><con:endpoint>http://lfr003015:8080/wsBiblio/OuvrageService</con:endpoint><con:request><![CDATA[<soapenv:Envelope xmlns:soapenv="http://schemas.xmlsoap.org/soap/envelope/" xmlns:web="http://webService.wsBiblio.khady.fr/">\r
   <soapenv:Header/>\r
   <soapenv:Body>\r
      <web:trouverOuvrageParIsbnTitreAuteur>\r
         <!--Optional:-->\r
         <isbn>?</isbn>\r
         <!--Optional:-->\r
         <titre>?</titre>\r
         <!--Optional:-->\r
         <auteur>?</auteur>\r
         <!--Optional:-->\r
         <disponibilité>?</disponibilité>\r
      </web:trouverOuvrageParIsbnTitreAuteur>\r
   </soapenv:Body>\r
</soapenv:Envelope>]]></con:request><con:assertion type="SOAP Response" id="7ae5f53a-e0bf-41ad-84f4-196b928c8196" name="SOAP Response"/><con:credentials><con:authType>No Authorization</con:authType></con:credentials><con:jmsConfig JMSDeliveryMode="PERSISTENT"/><con:jmsPropertyConfig/><con:wsaConfig mustUnderstand="NONE" version="200508" action="http://webService.wsBiblio.khady.fr/OuvrageService/trouverOuvrageParIsbnTitreAuteurRequest"/><con:wsrmConfig version="1.2"/></con:request></con:config></con:testStep><con:testStep type="request" id="797c7932-6729-4ba0-91cd-2c1861e14dcc" name="trouverOuvrageParId - Request 1"><con:settings/><con:config xsi:type="con:RequestStep" xmlns:xsi="http://www.w3.org/2001/XMLSchema-instance"><con:interface>OuvrageServicePortBinding</con:interface><con:operation>trouverOuvrageParId</con:operation><con:request name="trouverOuvrageParId - Request 1" outgoingWss="" incomingWss="" timeout="" sslKeystore="" useWsAddressing="false" useWsReliableMessaging="false" wssPasswordType="" id="2f6edcbc-28de-40c8-87cd-b08fa156d8a1"><con:settings/><con:encoding>UTF-8</con:encoding><con:endpoint>http://lfr003015:8080/wsBiblio/OuvrageService</con:endpoint><con:request><![CDATA[<soapenv:Envelope xmlns:soapenv="http://schemas.xmlsoap.org/soap/envelope/" xmlns:web="http://webService.wsBiblio.khady.fr/">\r
   <soapenv:Header/>\r
   <soapenv:Body>\r
      <web:trouverOuvrageParId>\r
         <idOuvrage>?</idOuvrage>\r
      </web:trouverOuvrageParId>\r
   </soapenv:Body>\r
</soapenv:Envelope>]]></con:request><con:assertion type="SOAP Response" id="f1ba9f0f-87b6-41f4-9a62-fe6a4f52b0b4" name="SOAP Response"/><con:credentials><con:authType>No Authorization</con:authType></con:credentials><con:jmsConfig JMSDeliveryMode="PERSISTENT"/><con:jmsPropertyConfig/><con:wsaConfig mustUnderstand="NONE" version="200508" action="http://webService.wsBiblio.khady.fr/OuvrageService/trouverOuvrageParIdRequest"/><con:wsrmConfig version="1.2"/></con:request></con:config></con:testStep><con:properties><con:property><con:name>id</con:name><con:value>1</con:value></con:property><con:property><con:name>isbn</con:name><con:value>2-8765-4301-XY</con:value></con:property><con:property><con:name>titre</con:name><con:value>Titre</con:value></con:property><con:property><con:name>resume</con:name><con:value>Lorem ipsum dolor sit amet, consectetur adipiscing elit. Nullam non orci ut ante auctor porta et ac quam. Cras id neque non tellus dignissim mattis.</con:value></con:property><con:property><con:name>nbrpage</con:name><con:value>100</con:value></con:property><con:property><con:name>dateParution</con:name><con:value/></con:property><con:property><con:name>dispo</con:name><con:value>true</con:value></con:property><con:property><con:name>photo</con:name><con:value/></con:property><con:property><con:name>categorie</con:name><con:value>1</con:value></con:property><con:property><con:name>auteur</con:name><con:value>1</con:value></con:property></con:properties></con:testCase><con:properties/></con:testSuite><con:properties/><con:wssContainer/><con:oAuth2ProfileContainer/><con:oAuth1ProfileContainer/></con:soapui-project>